{"RER": [["Move to Cajun restaurant.", ["Cajun restaurant"]], ["In a straight line, make your way to Catfish Station, which is your stop", ["Catfish Station"]], ["Go straight across Kirby Drive until you reach Catfish Station.", ["Catfish Station", "Kirby Drive"]], ["Go straight to Catfish Station.", ["Catfish Station"]], ["Go straight to Catfish Station", ["Catfish Station"]], ["Travel to Catfish Station but avoid Viet's Express.", ["Viet's Express", "Catfish Station"]], ["move to Catfish Station and avoid Viet's Express", ["Viet's Express", "Catfish Station"]], ["Navigate West on La Concha Lane and arrive at Catfish Station without going near TGF Hair Salon.", ["La Concha Lane", "Catfish Station", "TGF Hair Salon"]], ["Navigate to the Catfish Station while avoiding Viet's Express.", ["Viet's Express", "Catfish Station"]], ["Go to Catfish Station.", ["Catfish Station"]], ["Navigate to Viet's Express while passing through Catfish Station.", ["Viet's Express", "Catfish Station"]], ["Go straight until you reach Catfish station and then head northeast to Wet's Express.", ["Catfish station", "Wet's Express"]], ["Move to Viet's Express, but go to Catfish Station first.", ["Viet's Express", "Catfish Station"]], ["Make your way to Catfish Station and stop, then make your next stop at Viet's Express", ["Viet's Express", "Catfish Station"]], ["Proceed through the restaurant and make your way to Viet's Express.", ["Viet's Express"]], ["Go to the Cajun restaurant and then to Viet's Express", ["Viet's Express", "Cajun restaurant"]], ["Move to the Cajun restaurant and then to the Vietnamese restaurant.", ["Vietnamese restaurant", "Cajun restaurant"]], ["Navigate straight ahead to the Catfish Station and then travel northeast until you arrive at the Viet's Express.", ["Viet's Express", "Catfish Station"]], ["Go to Catfish Station while on your way to Viet's Express", ["Viet's Express", "Catfish Station"]], ["Proceed to Catfish Station and take a sharp right  45 degree turn.", ["Catfish Station"]], ["Travel directly to TGF Hair Salon then go to Catfish Station.", ["Catfish Station", "TGF Hair Salon"]], ["Pass the Hair Salon and land at your destination Catfish Station.", ["Catfish Station", "Hair Salon"]], ["Head to TGF Hair Salon, then go to Catfish Station.", ["Catfish Station", "TGF Hair Salon"]], ["Navigate to the Catfish Station from the TGF Hair Salon", ["Catfish Station", "TGF Hair Salon"]], ["Go to TGF Hair Salon while on your way to Catfish Station", ["Catfish Station", "TGF Hair Salon"]], ["Navigate to Catfish Station while passing through TGF Hair Salon.", ["Catfish Station", "TGF Hair Salon"]], ["Make a stop at TGF Hair Salon on the way to Catfish Station", ["Catfish Station", "TGF Hair Salon"]], ["Navigate to TGF hair salon on your way to the Cajun restaurant.", ["TGF hair salon", "Cajun restaurant"]], ["Move to Catfish station but be sure to proceed through TGF hair salon.", ["TGF hair salon", "Catfish station"]], ["Go straight to TGF Hair Salon and then go northeast to Catfish Station.", ["Catfish Station", "TGF Hair Salon"]], ["Avoid Catfish Station on the way to TGF Hair Salon.", ["Catfish Station", "TGF Hair Salon"]], ["Navigate to Viet 's Express on your way to TGT Hair Salon.", ["TGT Hair Salon", "Viet 's Express"]], ["Avoid Catfish Station while on your way to TGF Hair Salon", ["Catfish Station", "TGF Hair Salon"]], ["Go straight to Wet's Express and then turn left to TGF Hair Salon.", ["TGF Hair Salon", "Wet's Express"]], ["Take the most direct route to Viet's Express then continue southwest to TGF Hair Salon.", ["Viet's Express", "TGF Hair Salon"]], ["Please go to Viet's Express and then head to TGF Hair Salon", ["Viet's Express", "TGF Hair Salon"]], ["Navigate through Viet's Express and enter the TGF Hair salon", ["Viet's Express", "TGF Hair salon"]], ["go to the vietnamese restaurant and then the hair salon", ["hair salon", "vietnamese restaurant"]], ["Visit Viet's Express restaurant on your way to the Hair Salon", ["Viet's Express restaurant", "Hair Salon"]], ["Navigate to the vietnamese restaurant and then to the hair salon.", ["hair salon", "vietnamese restaurant"]]], "Grounding": {"Viet's Express": ["Viet's Express", "Office Depot"], "Wet's Express": ["Office Depot", "Royal Nails & Spa"], "Hair Salon": ["TGF Hair Salon", "Royal Nails & Spa"], "Kirby Drive": ["GameStop", "North Kirby Lot"], "Viet 's Express": ["Viet's Express", "Pizza Hut"], "Catfish station": ["Catfish Station", "Fannin Substation"], "Vietnamese restaurant": ["Viet's Express", "Akashi Asian Sushi Cuisine & Wine Bar"], "Viet's Express restaurant": ["Viet's Express", "Akashi Asian Sushi Cuisine & Wine Bar"], "La Concha Lane": ["Taco Cabana", "Domain at Kirby"], "Catfish Station": ["Catfish Station", "Fannin Substation"], "Cajun restaurant": ["Taco Cabana", "Akashi Asian Sushi Cuisine & Wine Bar"], "TGT Hair Salon": ["TGF Hair Salon", "Royal Nails & Spa"], "vietnamese restaurant": ["Viet's Express", "Akashi Asian Sushi Cuisine & Wine Bar"], "hair salon": ["TGF Hair Salon", "Royal Nails & Spa"], "TGF hair salon": ["TGF Hair Salon", "Royal Nails & Spa"], "TGF Hair salon": ["TGF Hair Salon", "Royal Nails & Spa"], "TGF Hair Salon": ["TGF Hair Salon", "Royal Nails & Spa"]}, "Placeholder maps": [{"Taco Cabana": "a"}, {"Catfish Station": "a"}, {"GameStop": "a", "Catfish Station": "b"}, {"Catfish Station": "a"}, {"Catfish Station": "a"}, {"Viet's Express": "a", "Catfish Station": "b"}, {"Viet's Express": "a", "Catfish Station": "b"}, {"Taco Cabana": "a", "Catfish Station": "b", "TGF Hair Salon": "c"}, {"Viet's Express": "a", "Catfish Station": "b"}, {"Catfish Station": "a"}, {"Viet's Express": "a", "Catfish Station": "b"}, {"Office Depot": "a", "Catfish Station": "b"}, {"Viet's Express": "a", "Catfish Station": "b"}, {"Viet's Express": "a", "Catfish Station": "b"}, {"Viet's Express": "a"}, {"Taco Cabana": "a", "Viet's Express": "b"}, {"Viet's Express": "a", "Taco Cabana": "b"}, {"Viet's Express": "a", "Catfish Station": "b"}, {"Viet's Express": "a", "Catfish Station": "b"}, {"Catfish Station": "a"}, {"Catfish Station": "a", "TGF Hair Salon": "b"}, {"Catfish Station": "a", "TGF Hair Salon": "b"}, {"Catfish Station": "a", "TGF Hair Salon": "b"}, {"Catfish Station": "a", "TGF Hair Salon": "b"}, {"Catfish Station": "a", "TGF Hair Salon": "b"}, {"Catfish Station": "a", "TGF Hair Salon": "b"}, {"Catfish Station": "a", "TGF Hair Salon": "b"}, {"Taco Cabana": "a", "TGF Hair Salon": "b"}, {"Catfish Station": "a", "TGF Hair Salon": "b"}, {"Catfish Station": "a", "TGF Hair Salon": "b"}, {"Catfish Station": "a", "TGF Hair Salon": "b"}, {"Viet's Express": "a", "TGF Hair Salon": "b"}, {"Catfish Station": "a", "TGF Hair Salon": "b"}, {"Office Depot": "a", "TGF Hair Salon": "b"}, {"Viet's Express": "a", "TGF Hair Salon": "b"}, {"Viet's Express": "a", "TGF Hair Salon": "b"}, {"Viet's Express": "a", "TGF Hair Salon": "b"}, {"Viet's Express": "a", "TGF Hair Salon": "b"}, {"Viet's Express": "a", "TGF Hair Salon": "b"}, {"Viet's Express": "a", "TGF Hair Salon": "b"}], "Input utterances": ["Move to Cajun restaurant.", "In a straight line, make your way to Catfish Station, which is your stop", "Go straight across Kirby Drive until you reach Catfish Station.", "Go straight to Catfish Station.", "Go straight to Catfish Station", "Travel to Catfish Station but avoid Viet's Express.", "move to Catfish Station and avoid Viet's Express", "Navigate West on La Concha Lane and arrive at Catfish Station without going near TGF Hair Salon.", "Navigate to the Catfish Station while avoiding Viet's Express.", "Go to Catfish Station.", "Navigate to Viet's Express while passing through Catfish Station.", "Go straight until you reach Catfish station and then head northeast to Wet's Express.", "Move to Viet's Express, but go to Catfish Station first.", "Make your way to Catfish Station and stop, then make your next stop at Viet's Express", "Proceed through the restaurant and make your way to Viet's Express.", "Go to the Cajun restaurant and then to Viet's Express", "Move to the Cajun restaurant and then to the Vietnamese restaurant.", "Navigate straight ahead to the Catfish Station and then travel northeast until you arrive at the Viet's Express.", "Go to Catfish Station while on your way to Viet's Express", "Proceed to Catfish Station and take a sharp right  45 degree turn.", "Travel directly to TGF Hair Salon then go to Catfish Station.", "Pass the Hair Salon and land at your destination Catfish Station.", "Head to TGF Hair Salon, then go to Catfish Station.", "Navigate to the Catfish Station from the TGF Hair Salon", "Go to TGF Hair Salon while on your way to Catfish Station", "Navigate to Catfish Station while passing through TGF Hair Salon.", "Make a stop at TGF Hair Salon on the way to Catfish Station", "Navigate to TGF hair salon on your way to the Cajun restaurant.", "Move to Catfish station but be sure to proceed through TGF hair salon.", "Go straight to TGF Hair Salon and then go northeast to Catfish Station.", "Avoid Catfish Station on the way to TGF Hair Salon.", "Navigate to Viet 's Express on your way to TGT Hair Salon.", "Avoid Catfish Station while on your way to TGF Hair Salon", "Go straight to Wet's Express and then turn left to TGF Hair Salon.", "Take the most direct route to Viet's Express then continue southwest to TGF Hair Salon.", "Please go to Viet's Express and then head to TGF Hair Salon", "Navigate through Viet's Express and enter the TGF Hair salon", "go to the vietnamese restaurant and then the hair salon", "Visit Viet's Express restaurant on your way to the Hair Salon", "Navigate to the vietnamese restaurant and then to the hair salon."], "Output Symbolic LTLs": ["F a", "G F a", "U a b", "F a", "F a", "& U ! a b F b", "& G ! a F b", "& U ! b a F b", "& U ! a b F b", "F a", "F & b F a", "U b F a", "F & a F b", "F & b F a", "F & d F & c F & b F a", "F & a F b", "F & b F a", "F & b F & a", "F & a F b", "F a", "F & b F a", "F & b F a", "F & b F a", "F & b F a", "F & a F b", "F & b F a", "F & b F a", "F & b F a", "F & a F b", "F & b F a", "U ! a b", "F & a F b", "U ! a b", "F & a F b", "F & a F b", "F & a F b", "F & a F b", "F & a F b", "F & a F b", "F & a F b"], "Output Grounded LTLs": ["F taco_cabana", "G F catfish_station", "U gamestop catfish_station", "F catfish_station", "F catfish_station", "& U ! viets_express catfish_station F catfish_station", "& G ! viets_express F catfish_station", "& U ! catfish_station taco_cabana F catfish_station", "& U ! viets_express catfish_station F catfish_station", "F catfish_station", "F & catfish_station F viets_express", "U catfish_station F office_depot", "F & viets_express F catfish_station", "F & catfish_station F viets_express", "F & d F & c F & b F viets_express", "F & taco_cabana F viets_express", "F & taco_cabana F viets_express", "F & catfish_station F & viets_express", "F & viets_express F catfish_station", "F catfish_station", "F & tgf_hair_salon F catfish_station", "F & tgf_hair_salon F catfish_station", "F & tgf_hair_salon F catfish_station", "F & tgf_hair_salon F catfish_station", "F & catfish_station F tgf_hair_salon", "F & tgf_hair_salon F catfish_station", "F & tgf_hair_salon F catfish_station", "F & tgf_hair_salon F taco_cabana", "F & catfish_station F tgf_hair_salon", "F & tgf_hair_salon F catfish_station", "U ! catfish_station tgf_hair_salon", "F & viets_express F tgf_hair_salon", "U ! catfish_station tgf_hair_salon", "F & office_depot F tgf_hair_salon", "F & viets_express F tgf_hair_salon", "F & viets_express F tgf_hair_salon", "F & viets_express F tgf_hair_salon", "F & viets_express F tgf_hair_salon", "F & viets_express F tgf_hair_salon", "F & viets_express F tgf_hair_salon"], "True Grounded LTLs": ["F catfish_station", "F catfish_station", "F catfish_station", "F catfish_station", "F catfish_station", "F catfish_station", "F catfish_station", "F catfish_station", "F catfish_station", "F catfish_station", "F & catfish_station F viets_express", "F & catfish_station F viets_express", "F & catfish_station F viets_express", "F & catfish_station F viets_express", "F & catfish_station F viets_express", "F & catfish_station F viets_express", "F & catfish_station F viets_express", "F & catfish_station F viets_express", "F & catfish_station F viets_express", "F & catfish_station F viets_express", "F & tgf_hair_salon F catfish_station", "F & tgf_hair_salon F catfish_station", "F & tgf_hair_salon F catfish_station", "F & tgf_hair_salon F catfish_station", "F & tgf_hair_salon F catfish_station", "F & tgf_hair_salon F catfish_station", "F & tgf_hair_salon F catfish_station", "F & tgf_hair_salon F catfish_station", "F & tgf_hair_salon F catfish_station", "F & tgf_hair_salon F catfish_station", "F & viets_express F tgf_hair_salon", "F & viets_express F tgf_hair_salon", "F & viets_express F tgf_hair_salon", "F & viets_express F tgf_hair_salon", "F & viets_express F tgf_hair_salon", "F & viets_express F tgf_hair_salon", "F & viets_express F tgf_hair_salon", "F & viets_express F tgf_hair_salon", "F & viets_express F tgf_hair_salon", "F & viets_express F tgf_hair_salon"], "Meta": [["visit", 1, "New York #1"], ["visit", 1, "New York #1"], ["visit", 1, "New York #1"], ["visit", 1, "New York #1"], ["visit", 1, "New York #1"], ["visit", 1, "New York #1"], ["visit", 1, "New York #1"], ["visit", 1, "New York #1"], ["visit", 1, "New York #1"], ["visit", 1, "New York #1"], ["visit", 2, "New York #1"], ["visit", 2, "New York #1"], ["visit", 2, "New York #1"], ["visit", 2, "New York #1"], ["visit", 2, "New York #1"], ["visit", 2, "New York #1"], ["visit", 2, "New York #1"], ["visit", 2, "New York #1"], ["visit", 2, "New York #1"], ["visit", 2, "New York #1"], ["visit", 2, "New York #1"], ["visit", 2, "New York #1"], ["visit", 2, "New York #1"], ["visit", 2, "New York #1"], ["visit", 2, "New York #1"], ["visit", 2, "New York #1"], ["visit", 2, "New York #1"], ["visit", 2, "New York #1"], ["visit", 2, "New York #1"], ["visit", 2, "New York #1"], ["visit", 2, "New York #1"], ["visit", 2, "New York #1"], ["visit", 2, "New York #1"], ["visit", 2, "New York #1"], ["visit", 2, "New York #1"], ["visit", 2, "New York #1"], ["visit", 2, "New York #1"], ["visit", 2, "New York #1"], ["visit", 2, "New York #1"], ["visit", 2, "New York #1"], ["visit", 1, "New York #2"], ["visit", 1, "New York #2"], ["visit", 1, "New York #2"], ["visit", 1, "New York #2"], ["visit", 1, "New York #2"], ["visit", 1, "New York #2"], ["visit", 1, "New York #2"], ["visit", 1, "New York #2"], ["visit", 1, "New York #2"], ["visit", 1, "New York #2"], ["visit", 2, "New York #2"], ["visit", 2, "New York #2"], ["visit", 2, "New York #2"], ["visit", 2, "New York #2"], ["visit", 2, "New York #2"], ["visit", 2, "New York #2"], ["visit", 2, "New York #2"], ["visit", 2, "New York #2"], ["visit", 2, "New York #2"], ["visit", 2, "New York #2"], ["visit", 2, "New York #2"], ["visit", 2, "New York #2"], ["visit", 2, "New York #2"], ["visit", 2, "New York #2"], ["visit", 2, "New York #2"], ["visit", 2, "New York #2"], ["visit", 2, "New York #2"], ["visit", 2, "New York #2"], ["visit", 2, "New York #2"], ["visit", 2, "New York #2"], ["visit", 2, "New York #2"], ["visit", 2, "New York #2"], ["visit", 2, "New York #2"], ["visit", 2, "New York #2"], ["visit", 2, "New York #2"], ["visit", 2, "New York #2"], ["visit", 2, "New York #2"], ["visit", 2, "New York #2"], ["visit", 2, "New York #2"], ["visit", 2, "New York #2"], ["visit", 1, "Los Angeles #1"], ["visit", 1, "Los Angeles #1"], ["visit", 1, "Los Angeles #1"], ["visit", 1, "Los Angeles #1"], ["visit", 1, "Los Angeles #1"], ["visit", 1, "Los Angeles #1"], ["visit", 1, "Los Angeles #1"], ["visit", 1, "Los Angeles #1"], ["visit", 1, "Los Angeles #1"], ["visit", 1, "Los Angeles #1"], ["visit", 2, "Los Angeles #1"], ["visit", 2, "Los Angeles #1"], ["visit", 2, "Los Angeles #1"], ["visit", 2, "Los Angeles #1"], ["visit", 2, "Los Angeles #1"], ["visit", 2, "Los Angeles #1"], ["visit", 2, "Los Angeles #1"], ["visit", 2, "Los Angeles #1"], ["visit", 2, "Los Angeles #1"], ["visit", 2, "Los Angeles #1"], ["visit", 2, "Los Angeles #1"], ["visit", 2, "Los Angeles #1"], ["visit", 2, "Los Angeles #1"], ["visit", 2, "Los Angeles #1"], ["visit", 2, "Los Angeles #1"], ["visit", 2, "Los Angeles #1"], ["visit", 2, "Los Angeles #1"], ["visit", 2, "Los Angeles #1"], ["visit", 2, "Los Angeles #1"], ["visit", 2, "Los Angeles #1"], ["visit", 2, "Los Angeles #1"], ["visit", 2, "Los Angeles #1"], ["visit", 2, "Los Angeles #1"], ["visit", 2, "Los Angeles #1"], ["visit", 2, "Los Angeles #1"], ["visit", 2, "Los Angeles #1"], ["visit", 2, "Los Angeles #1"], ["visit", 2, "Los Angeles #1"], ["visit", 2, "Los Angeles #1"], ["visit", 2, "Los Angeles #1"], ["visit", 1, "Los Angeles #2"], ["visit", 1, "Los Angeles #2"], ["visit", 1, "Los Angeles #2"], ["visit", 1, "Los Angeles #2"], ["visit", 1, "Los Angeles #2"], ["visit", 1, "Los Angeles #2"], ["visit", 1, "Los Angeles #2"], ["visit", 1, "Los Angeles #2"], ["visit", 1, "Los Angeles #2"], ["visit", 1, "Los Angeles #2"], ["visit", 2, "Los Angeles #2"], ["visit", 2, "Los Angeles #2"], ["visit", 2, "Los Angeles #2"], ["visit", 2, "Los Angeles #2"], ["visit", 2, "Los Angeles #2"], ["visit", 2, "Los Angeles #2"], ["visit", 2, "Los Angeles #2"], ["visit", 2, "Los Angeles #2"], ["visit", 2, "Los Angeles #2"], ["visit", 2, "Los Angeles #2"], ["visit", 2, "Los Angeles #2"], ["visit", 2, "Los Angeles #2"], ["visit", 2, "Los Angeles #2"], ["visit", 2, "Los Angeles #2"], ["visit", 2, "Los Angeles #2"], ["visit", 2, "Los Angeles #2"], ["visit", 2, "Los Angeles #2"], ["visit", 2, "Los Angeles #2"], ["visit", 2, "Los Angeles #2"], ["visit", 2, "Los Angeles #2"], ["visit", 2, "Los Angeles #2"], ["visit", 2, "Los Angeles #2"], ["visit", 2, "Los Angeles #2"], ["visit", 2, "Los Angeles #2"], ["visit", 2, "Los Angeles #2"], ["visit", 2, "Los Angeles #2"], ["visit", 2, "Los Angeles #2"], ["visit", 2, "Los Angeles #2"], ["visit", 2, "Los Angeles #2"], ["visit", 2, "Los Angeles #2"], ["visit", 1, "Chicago #1"], ["visit", 1, "Chicago #1"], ["visit", 1, "Chicago #1"], ["visit", 1, "Chicago #1"], ["visit", 1, "Chicago #1"], ["visit", 1, "Chicago #1"], ["visit", 1, "Chicago #1"], ["visit", 1, "Chicago #1"], ["visit", 1, "Chicago #1"], ["visit", 1, "Chicago #1"], ["visit", 2, "Chicago #1"], ["visit", 2, "Chicago #1"], ["visit", 2, "Chicago #1"], ["visit", 2, "Chicago #1"], ["visit", 2, "Chicago #1"], ["visit", 2, "Chicago #1"], ["visit", 2, "Chicago #1"], ["visit", 2, "Chicago #1"], ["visit", 2, "Chicago #1"], ["visit", 2, "Chicago #1"], ["visit", 2, "Chicago #1"], ["visit", 2, "Chicago #1"], ["visit", 2, "Chicago #1"], ["visit", 2, "Chicago #1"], ["visit", 2, "Chicago #1"], ["visit", 2, "Chicago #1"], ["visit", 2, "Chicago #1"], ["visit", 2, "Chicago #1"], ["visit", 2, "Chicago #1"], ["visit", 2, "Chicago #1"], ["visit", 2, "Chicago #1"], ["visit", 2, "Chicago #1"], ["visit", 2, "Chicago #1"], ["visit", 2, "Chicago #1"], ["visit", 2, "Chicago #1"], ["visit", 2, "Chicago #1"], ["visit", 2, "Chicago #1"], ["visit", 2, "Chicago #1"], ["visit", 2, "Chicago #1"], ["visit", 2, "Chicago #1"], ["visit", 1, "Chicago #2"], ["visit", 1, "Chicago #2"], ["visit", 1, "Chicago #2"], ["visit", 1, "Chicago #2"], ["visit", 1, "Chicago #2"], ["visit", 1, "Chicago #2"], ["visit", 1, "Chicago #2"], ["visit", 1, "Chicago #2"], ["visit", 1, "Chicago #2"], ["visit", 1, "Chicago #2"], ["visit", 2, "Chicago #2"], ["visit", 2, "Chicago #2"], ["visit", 2, "Chicago #2"], ["visit", 2, "Chicago #2"], ["visit", 2, "Chicago #2"], ["visit", 2, "Chicago #2"], ["visit", 2, "Chicago #2"], ["visit", 2, "Chicago #2"], ["visit", 2, "Chicago #2"], ["visit", 2, "Chicago #2"], ["visit", 2, "Chicago #2"], ["visit", 2, "Chicago #2"], ["visit", 2, "Chicago #2"], ["visit", 2, "Chicago #2"], ["visit", 2, "Chicago #2"], ["visit", 2, "Chicago #2"], ["visit", 2, "Chicago #2"], ["visit", 2, "Chicago #2"], ["visit", 2, "Chicago #2"], ["visit", 2, "Chicago #2"], ["visit", 2, "Chicago #2"], ["visit", 2, "Chicago #2"], ["visit", 2, "Chicago #2"], ["visit", 2, "Chicago #2"], ["visit", 2, "Chicago #2"], ["visit", 2, "Chicago #2"], ["visit", 2, "Chicago #2"], ["visit", 2, "Chicago #2"], ["visit", 2, "Chicago #2"], ["visit", 2, "Chicago #2"], ["visit", 1, "Houston"], ["visit", 1, "Houston"], ["visit", 1, "Houston"], ["visit", 1, "Houston"], ["visit", 1, "Houston"], ["visit", 1, "Houston"], ["visit", 1, "Houston"], ["visit", 1, "Houston"], ["visit", 1, "Houston"], ["visit", 1, "Houston"], ["visit", 2, "Houston"], ["visit", 2, "Houston"], ["visit", 2, "Houston"], ["visit", 2, "Houston"], ["visit", 2, "Houston"], ["visit", 2, "Houston"], ["visit", 2, "Houston"], ["visit", 2, "Houston"], ["visit", 2, "Houston"], ["visit", 2, "Houston"], ["visit", 2, "Houston"], ["visit", 2, "Houston"], ["visit", 2, "Houston"], ["visit", 2, "Houston"], ["visit", 2, "Houston"], ["visit", 2, "Houston"], ["visit", 2, "Houston"], ["visit", 2, "Houston"], ["visit", 2, "Houston"], ["visit", 2, "Houston"], ["visit", 2, "Houston"], ["visit", 2, "Houston"], ["visit", 2, "Houston"], ["visit", 2, "Houston"], ["visit", 2, "Houston"], ["visit", 2, "Houston"], ["visit", 2, "Houston"], ["visit", 2, "Houston"], ["visit", 2, "Houston"], ["visit", 2, "Houston"], ["visit", 1, "Philadelphia #1"], ["visit", 1, "Philadelphia #1"], ["visit", 1, "Philadelphia #1"], ["visit", 1, "Philadelphia #1"], ["visit", 1, "Philadelphia #1"], ["visit", 1, "Philadelphia #1"], ["visit", 1, "Philadelphia #1"], ["visit", 1, "Philadelphia #1"], ["visit", 1, "Philadelphia #1"], ["visit", 1, "Philadelphia #1"], ["visit", 2, "Philadelphia #1"], ["visit", 2, "Philadelphia #1"], ["visit", 2, "Philadelphia #1"], ["visit", 2, "Philadelphia #1"], ["visit", 2, "Philadelphia #1"], ["visit", 2, "Philadelphia #1"], ["visit", 2, "Philadelphia #1"], ["visit", 2, "Philadelphia #1"], ["visit", 2, "Philadelphia #1"], ["visit", 2, "Philadelphia #1"], ["visit", 2, "Philadelphia #1"], ["visit", 2, "Philadelphia #1"], ["visit", 2, "Philadelphia #1"], ["visit", 2, "Philadelphia #1"], ["visit", 2, "Philadelphia #1"], ["visit", 2, "Philadelphia #1"], ["visit", 2, "Philadelphia #1"], ["visit", 2, "Philadelphia #1"], ["visit", 2, "Philadelphia #1"], ["visit", 2, "Philadelphia #1"], ["visit", 2, "Philadelphia #1"], ["visit", 2, "Philadelphia #1"], ["visit", 2, "Philadelphia #1"], ["visit", 2, "Philadelphia #1"], ["visit", 2, "Philadelphia #1"], ["visit", 2, "Philadelphia #1"], ["visit", 2, "Philadelphia #1"], ["visit", 2, "Philadelphia #1"], ["visit", 2, "Philadelphia #1"], ["visit", 2, "Philadelphia #1"], ["visit", 1, "Philadelphia #2"], ["visit", 1, "Philadelphia #2"], ["visit", 1, "Philadelphia #2"], ["visit", 1, "Philadelphia #2"], ["visit", 1, "Philadelphia #2"], ["visit", 1, "Philadelphia #2"], ["visit", 1, "Philadelphia #2"], ["visit", 1, "Philadelphia #2"], ["visit", 1, "Philadelphia #2"], ["visit", 1, "Philadelphia #2"], ["visit", 2, "Philadelphia #2"], ["visit", 2, "Philadelphia #2"], ["visit", 2, "Philadelphia #2"], ["visit", 2, "Philadelphia #2"], ["visit", 2, "Philadelphia #2"], ["visit", 2, "Philadelphia #2"], ["visit", 2, "Philadelphia #2"], ["visit", 2, "Philadelphia #2"], ["visit", 2, "Philadelphia #2"], ["visit", 2, "Philadelphia #2"], ["visit", 2, "Philadelphia #2"], ["visit", 2, "Philadelphia #2"], ["visit", 2, "Philadelphia #2"], ["visit", 2, "Philadelphia #2"], ["visit", 2, "Philadelphia #2"], ["visit", 2, "Philadelphia #2"], ["visit", 2, "Philadelphia #2"], ["visit", 2, "Philadelphia #2"], ["visit", 2, "Philadelphia #2"], ["visit", 2, "Philadelphia #2"], ["visit", 2, "Philadelphia #2"], ["visit", 2, "Philadelphia #2"], ["visit", 2, "Philadelphia #2"], ["visit", 2, "Philadelphia #2"], ["visit", 2, "Philadelphia #2"], ["visit", 2, "Philadelphia #2"], ["visit", 2, "Philadelphia #2"], ["visit", 2, "Philadelphia #2"], ["visit", 2, "Philadelphia #2"], ["visit", 2, "Philadelphia #2"], ["visit", 1, "San Diego #1"], ["visit", 1, "San Diego #1"], ["visit", 1, "San Diego #1"], ["visit", 1, "San Diego #1"], ["visit", 1, "San Diego #1"], ["visit", 1, "San Diego #1"], ["visit", 1, "San Diego #1"], ["visit", 1, "San Diego #1"], ["visit", 1, "San Diego #1"], ["visit", 1, "San Diego #1"], ["visit", 2, "San Diego #1"], ["visit", 2, "San Diego #1"], ["visit", 2, "San Diego #1"], ["visit", 2, "San Diego #1"], ["visit", 2, "San Diego #1"], ["visit", 2, "San Diego #1"], ["visit", 2, "San Diego #1"], ["visit", 2, "San Diego #1"], ["visit", 2, "San Diego #1"], ["visit", 2, "San Diego #1"], ["visit", 2, "San Diego #1"], ["visit", 2, "San Diego #1"], ["visit", 2, "San Diego #1"], ["visit", 2, "San Diego #1"], ["visit", 2, "San Diego #1"], ["visit", 2, "San Diego #1"], ["visit", 2, "San Diego #1"], ["visit", 2, "San Diego #1"], ["visit", 2, "San Diego #1"], ["visit", 2, "San Diego #1"], ["visit", 2, "San Diego #1"], ["visit", 2, "San Diego #1"], ["visit", 2, "San Diego #1"], ["visit", 2, "San Diego #1"], ["visit", 2, "San Diego #1"], ["visit", 2, "San Diego #1"], ["visit", 2, "San Diego #1"], ["visit", 2, "San Diego #1"], ["visit", 2, "San Diego #1"], ["visit", 2, "San Diego #1"], ["visit", 1, "San Diego #2"], ["visit", 1, "San Diego #2"], ["visit", 1, "San Diego #2"], ["visit", 1, "San Diego #2"], ["visit", 1, "San Diego #2"], ["visit", 1, "San Diego #2"], ["visit", 1, "San Diego #2"], ["visit", 1, "San Diego #2"], ["visit", 1, "San Diego #2"], ["visit", 1, "San Diego #2"], ["visit", 2, "San Diego #2"], ["visit", 2, "San Diego #2"], ["visit", 2, "San Diego #2"], ["visit", 2, "San Diego #2"], ["visit", 2, "San Diego #2"], ["visit", 2, "San Diego #2"], ["visit", 2, "San Diego #2"], ["visit", 2, "San Diego #2"], ["visit", 2, "San Diego #2"], ["visit", 2, "San Diego #2"], ["visit", 2, "San Diego #2"], ["visit", 2, "San Diego #2"], ["visit", 2, "San Diego #2"], ["visit", 2, "San Diego #2"], ["visit", 2, "San Diego #2"], ["visit", 2, "San Diego #2"], ["visit", 2, "San Diego #2"], ["visit", 2, "San Diego #2"], ["visit", 2, "San Diego #2"], ["visit", 2, "San Diego #2"], ["visit", 1, "Jacksonville #1"], ["visit", 1, "Jacksonville #1"], ["visit", 1, "Jacksonville #1"], ["visit", 1, "Jacksonville #1"], ["visit", 1, "Jacksonville #1"], ["visit", 1, "Jacksonville #1"], ["visit", 1, "Jacksonville #1"], ["visit", 1, "Jacksonville #1"], ["visit", 1, "Jacksonville #1"], ["visit", 1, "Jacksonville #1"], ["visit", 2, "Jacksonville #1"], ["visit", 2, "Jacksonville #1"], ["visit", 2, "Jacksonville #1"], ["visit", 2, "Jacksonville #1"], ["visit", 2, "Jacksonville #1"], ["visit", 2, "Jacksonville #1"], ["visit", 2, "Jacksonville #1"], ["visit", 2, "Jacksonville #1"], ["visit", 2, "Jacksonville #1"], ["visit", 2, "Jacksonville #1"], ["visit", 2, "Jacksonville #1"], ["visit", 2, "Jacksonville #1"], ["visit", 2, "Jacksonville #1"], ["visit", 2, "Jacksonville #1"], ["visit", 2, "Jacksonville #1"], ["visit", 2, "Jacksonville #1"], ["visit", 2, "Jacksonville #1"], ["visit", 2, "Jacksonville #1"], ["visit", 2, "Jacksonville #1"], ["visit", 2, "Jacksonville #1"], ["visit", 2, "Jacksonville #1"], ["visit", 2, "Jacksonville #1"], ["visit", 2, "Jacksonville #1"], ["visit", 2, "Jacksonville #1"], ["visit", 2, "Jacksonville #1"], ["visit", 2, "Jacksonville #1"], ["visit", 2, "Jacksonville #1"], ["visit", 2, "Jacksonville #1"], ["visit", 2, "Jacksonville #1"], ["visit", 2, "Jacksonville #1"], ["visit", 1, "Jacksonville #2"], ["visit", 1, "Jacksonville #2"], ["visit", 1, "Jacksonville #2"], ["visit", 1, "Jacksonville #2"], ["visit", 1, "Jacksonville #2"], ["visit", 1, "Jacksonville #2"], ["visit", 1, "Jacksonville #2"], ["visit", 1, "Jacksonville #2"], ["visit", 1, "Jacksonville #2"], ["visit", 1, "Jacksonville #2"], ["visit", 2, "Jacksonville #2"], ["visit", 2, "Jacksonville #2"], ["visit", 2, "Jacksonville #2"], ["visit", 2, "Jacksonville #2"], ["visit", 2, "Jacksonville #2"], ["visit", 2, "Jacksonville #2"], ["visit", 2, "Jacksonville #2"], ["visit", 2, "Jacksonville #2"], ["visit", 2, "Jacksonville #2"], ["visit", 2, "Jacksonville #2"], ["visit", 2, "Jacksonville #2"], ["visit", 2, "Jacksonville #2"], ["visit", 2, "Jacksonville #2"], ["visit", 2, "Jacksonville #2"], ["visit", 2, "Jacksonville #2"], ["visit", 2, "Jacksonville #2"], ["visit", 2, "Jacksonville #2"], ["visit", 2, "Jacksonville #2"], ["visit", 2, "Jacksonville #2"], ["visit", 2, "Jacksonville #2"], ["visit", 2, "Jacksonville #2"], ["visit", 2, "Jacksonville #2"], ["visit", 2, "Jacksonville #2"], ["visit", 2, "Jacksonville #2"], ["visit", 2, "Jacksonville #2"], ["visit", 2, "Jacksonville #2"], ["visit", 2, "Jacksonville #2"], ["visit", 2, "Jacksonville #2"], ["visit", 2, "Jacksonville #2"], ["visit", 2, "Jacksonville #2"], ["visit", 1, "Columbus #1"], ["visit", 1, "Columbus #1"], ["visit", 1, "Columbus #1"], ["visit", 1, "Columbus #1"], ["visit", 1, "Columbus #1"], ["visit", 1, "Columbus #1"], ["visit", 1, "Columbus #1"], ["visit", 1, "Columbus #1"], ["visit", 1, "Columbus #1"], ["visit", 1, "Columbus #1"], ["visit", 2, "Columbus #1"], ["visit", 2, "Columbus #1"], ["visit", 2, "Columbus #1"], ["visit", 2, "Columbus #1"], ["visit", 2, "Columbus #1"], ["visit", 2, "Columbus #1"], ["visit", 2, "Columbus #1"], ["visit", 2, "Columbus #1"], ["visit", 2, "Columbus #1"], ["visit", 2, "Columbus #1"], ["visit", 2, "Columbus #1"], ["visit", 2, "Columbus #1"], ["visit", 2, "Columbus #1"], ["visit", 2, "Columbus #1"], ["visit", 2, "Columbus #1"], ["visit", 2, "Columbus #1"], ["visit", 2, "Columbus #1"], ["visit", 2, "Columbus #1"], ["visit", 2, "Columbus #1"], ["visit", 2, "Columbus #1"], ["visit", 2, "Columbus #1"], ["visit", 2, "Columbus #1"], ["visit", 2, "Columbus #1"], ["visit", 2, "Columbus #1"], ["visit", 2, "Columbus #1"], ["visit", 2, "Columbus #1"], ["visit", 2, "Columbus #1"], ["visit", 2, "Columbus #1"], ["visit", 2, "Columbus #1"], ["visit", 2, "Columbus #1"], ["visit", 2, "Columbus #1"], ["visit", 2, "Columbus #1"], ["visit", 2, "Columbus #1"], ["visit", 2, "Columbus #1"], ["visit", 2, "Columbus #1"], ["visit", 2, "Columbus #1"], ["visit", 2, "Columbus #1"], ["visit", 2, "Columbus #1"], ["visit", 2, "Columbus #1"], ["visit", 2, "Columbus #1"], ["visit", 1, "Columbus #2"], ["visit", 1, "Columbus #2"], ["visit", 1, "Columbus #2"], ["visit", 1, "Columbus #2"], ["visit", 1, "Columbus #2"], ["visit", 1, "Columbus #2"], ["visit", 1, "Columbus #2"], ["visit", 1, "Columbus #2"], ["visit", 1, "Columbus #2"], ["visit", 1, "Columbus #2"], ["visit", 2, "Columbus #2"], ["visit", 2, "Columbus #2"], ["visit", 2, "Columbus #2"], ["visit", 2, "Columbus #2"], ["visit", 2, "Columbus #2"], ["visit", 2, "Columbus #2"], ["visit", 2, "Columbus #2"], ["visit", 2, "Columbus #2"], ["visit", 2, "Columbus #2"], ["visit", 2, "Columbus #2"], ["visit", 2, "Columbus #2"], ["visit", 2, "Columbus #2"], ["visit", 2, "Columbus #2"], ["visit", 2, "Columbus #2"], ["visit", 2, "Columbus #2"], ["visit", 2, "Columbus #2"], ["visit", 2, "Columbus #2"], ["visit", 2, "Columbus #2"], ["visit", 2, "Columbus #2"], ["visit", 2, "Columbus #2"], ["visit", 2, "Columbus #2"], ["visit", 2, "Columbus #2"], ["visit", 2, "Columbus #2"], ["visit", 2, "Columbus #2"], ["visit", 2, "Columbus #2"], ["visit", 2, "Columbus #2"], ["visit", 2, "Columbus #2"], ["visit", 2, "Columbus #2"], ["visit", 2, "Columbus #2"], ["visit", 2, "Columbus #2"], ["visit", 1, "Charlotte #1"], ["visit", 1, "Charlotte #1"], ["visit", 1, "Charlotte #1"], ["visit", 1, "Charlotte #1"], ["visit", 1, "Charlotte #1"], ["visit", 1, "Charlotte #1"], ["visit", 1, "Charlotte #1"], ["visit", 1, "Charlotte #1"], ["visit", 1, "Charlotte #1"], ["visit", 1, "Charlotte #1"], ["visit", 2, "Charlotte #1"], ["visit", 2, "Charlotte #1"], ["visit", 2, "Charlotte #1"], ["visit", 2, "Charlotte #1"], ["visit", 2, "Charlotte #1"], ["visit", 2, "Charlotte #1"], ["visit", 2, "Charlotte #1"], ["visit", 2, "Charlotte #1"], ["visit", 2, "Charlotte #1"], ["visit", 2, "Charlotte #1"], ["visit", 2, "Charlotte #1"], ["visit", 2, "Charlotte #1"], ["visit", 2, "Charlotte #1"], ["visit", 2, "Charlotte #1"], ["visit", 2, "Charlotte #1"], ["visit", 2, "Charlotte #1"], ["visit", 2, "Charlotte #1"], ["visit", 2, "Charlotte #1"], ["visit", 2, "Charlotte #1"], ["visit", 2, "Charlotte #1"], ["visit", 2, "Charlotte #1"], ["visit", 2, "Charlotte #1"], ["visit", 2, "Charlotte #1"], ["visit", 2, "Charlotte #1"], ["visit", 2, "Charlotte #1"], ["visit", 2, "Charlotte #1"], ["visit", 2, "Charlotte #1"], ["visit", 2, "Charlotte #1"], ["visit", 2, "Charlotte #1"], ["visit", 2, "Charlotte #1"], ["visit", 1, "Charlotte #2"], ["visit", 1, "Charlotte #2"], ["visit", 1, "Charlotte #2"], ["visit", 1, "Charlotte #2"], ["visit", 1, "Charlotte #2"], ["visit", 1, "Charlotte #2"], ["visit", 1, "Charlotte #2"], ["visit", 1, "Charlotte #2"], ["visit", 1, "Charlotte #2"], ["visit", 1, "Charlotte #2"], ["visit", 2, "Charlotte #2"], ["visit", 2, "Charlotte #2"], ["visit", 2, "Charlotte #2"], ["visit", 2, "Charlotte #2"], ["visit", 2, "Charlotte #2"], ["visit", 2, "Charlotte #2"], ["visit", 2, "Charlotte #2"], ["visit", 2, "Charlotte #2"], ["visit", 2, "Charlotte #2"], ["visit", 2, "Charlotte #2"], ["visit", 2, "Charlotte #2"], ["visit", 2, "Charlotte #2"], ["visit", 2, "Charlotte #2"], ["visit", 2, "Charlotte #2"], ["visit", 2, "Charlotte #2"], ["visit", 2, "Charlotte #2"], ["visit", 2, "Charlotte #2"], ["visit", 2, "Charlotte #2"], ["visit", 2, "Charlotte #2"], ["visit", 2, "Charlotte #2"], ["visit", 2, "Charlotte #2"], ["visit", 2, "Charlotte #2"], ["visit", 2, "Charlotte #2"], ["visit", 2, "Charlotte #2"], ["visit", 2, "Charlotte #2"], ["visit", 2, "Charlotte #2"], ["visit", 2, "Charlotte #2"], ["visit", 2, "Charlotte #2"], ["visit", 2, "Charlotte #2"], ["visit", 2, "Charlotte #2"], ["visit", 1, "Indianapolis"], ["visit", 1, "Indianapolis"], ["visit", 1, "Indianapolis"], ["visit", 1, "Indianapolis"], ["visit", 1, "Indianapolis"], ["visit", 1, "Indianapolis"], ["visit", 1, "Indianapolis"], ["visit", 1, "Indianapolis"], ["visit", 1, "Indianapolis"], ["visit", 1, "Indianapolis"], ["visit", 2, "Indianapolis"], ["visit", 2, "Indianapolis"], ["visit", 2, "Indianapolis"], ["visit", 2, "Indianapolis"], ["visit", 2, "Indianapolis"], ["visit", 2, "Indianapolis"], ["visit", 2, "Indianapolis"], ["visit", 2, "Indianapolis"], ["visit", 2, "Indianapolis"], ["visit", 2, "Indianapolis"], ["visit", 2, "Indianapolis"], ["visit", 2, "Indianapolis"], ["visit", 2, "Indianapolis"], ["visit", 2, "Indianapolis"], ["visit", 2, "Indianapolis"], ["visit", 2, "Indianapolis"], ["visit", 2, "Indianapolis"], ["visit", 2, "Indianapolis"], ["visit", 2, "Indianapolis"], ["visit", 2, "Indianapolis"], ["visit", 2, "Indianapolis"], ["visit", 2, "Indianapolis"], ["visit", 2, "Indianapolis"], ["visit", 2, "Indianapolis"], ["visit", 2, "Indianapolis"], ["visit", 2, "Indianapolis"], ["visit", 2, "Indianapolis"], ["visit", 2, "Indianapolis"], ["visit", 2, "Indianapolis"], ["visit", 2, "Indianapolis"], ["visit", 1, "Seattle"], ["visit", 1, "Seattle"], ["visit", 1, "Seattle"], ["visit", 1, "Seattle"], ["visit", 1, "Seattle"], ["visit", 1, "Seattle"], ["visit", 1, "Seattle"], ["visit", 1, "Seattle"], ["visit", 1, "Seattle"], ["visit", 1, "Seattle"], ["visit", 2, "Seattle"], ["visit", 2, "Seattle"], ["visit", 2, "Seattle"], ["visit", 2, "Seattle"], ["visit", 2, "Seattle"], ["visit", 2, "Seattle"], ["visit", 2, "Seattle"], ["visit", 2, "Seattle"], ["visit", 2, "Seattle"], ["visit", 2, "Seattle"], ["visit", 2, "Seattle"], ["visit", 2, "Seattle"], ["visit", 2, "Seattle"], ["visit", 2, "Seattle"], ["visit", 2, "Seattle"], ["visit", 2, "Seattle"], ["visit", 2, "Seattle"], ["visit", 2, "Seattle"], ["visit", 2, "Seattle"], ["visit", 2, "Seattle"], ["visit", 2, "Seattle"], ["visit", 2, "Seattle"], ["visit", 2, "Seattle"], ["visit", 2, "Seattle"], ["visit", 2, "Seattle"], ["visit", 2, "Seattle"], ["visit", 2, "Seattle"], ["visit", 2, "Seattle"], ["visit", 2, "Seattle"], ["visit", 2, "Seattle"], ["visit", 1, "Denver #1"], ["visit", 1, "Denver #1"], ["visit", 1, "Denver #1"], ["visit", 1, "Denver #1"], ["visit", 1, "Denver #1"], ["visit", 1, "Denver #1"], ["visit", 1, "Denver #1"], ["visit", 1, "Denver #1"], ["visit", 1, "Denver #1"], ["visit", 1, "Denver #1"], ["visit", 2, "Denver #1"], ["visit", 2, "Denver #1"], ["visit", 2, "Denver #1"], ["visit", 2, "Denver #1"], ["visit", 2, "Denver #1"], ["visit", 2, "Denver #1"], ["visit", 2, "Denver #1"], ["visit", 2, "Denver #1"], ["visit", 2, "Denver #1"], ["visit", 2, "Denver #1"], ["visit", 2, "Denver #1"], ["visit", 2, "Denver #1"], ["visit", 2, "Denver #1"], ["visit", 2, "Denver #1"], ["visit", 2, "Denver #1"], ["visit", 2, "Denver #1"], ["visit", 2, "Denver #1"], ["visit", 2, "Denver #1"], ["visit", 2, "Denver #1"], ["visit", 2, "Denver #1"], ["visit", 2, "Denver #1"], ["visit", 2, "Denver #1"], ["visit", 2, "Denver #1"], ["visit", 2, "Denver #1"], ["visit", 2, "Denver #1"], ["visit", 2, "Denver #1"], ["visit", 2, "Denver #1"], ["visit", 2, "Denver #1"], ["visit", 2, "Denver #1"], ["visit", 2, "Denver #1"], ["visit", 1, "Denver #2"], ["visit", 1, "Denver #2"], ["visit", 1, "Denver #2"], ["visit", 1, "Denver #2"], ["visit", 1, "Denver #2"], ["visit", 1, "Denver #2"], ["visit", 1, "Denver #2"], ["visit", 1, "Denver #2"], ["visit", 1, "Denver #2"], ["visit", 1, "Denver #2"], ["visit", 2, "Denver #2"], ["visit", 2, "Denver #2"], ["visit", 2, "Denver #2"], ["visit", 2, "Denver #2"], ["visit", 2, "Denver #2"], ["visit", 2, "Denver #2"], ["visit", 2, "Denver #2"], ["visit", 2, "Denver #2"], ["visit", 2, "Denver #2"], ["visit", 2, "Denver #2"], ["visit", 2, "Denver #2"], ["visit", 2, "Denver #2"], ["visit", 2, "Denver #2"], ["visit", 2, "Denver #2"], ["visit", 2, "Denver #2"], ["visit", 2, "Denver #2"], ["visit", 2, "Denver #2"], ["visit", 2, "Denver #2"], ["visit", 2, "Denver #2"], ["visit", 2, "Denver #2"], ["visit", 2, "Denver #2"], ["visit", 2, "Denver #2"], ["visit", 2, "Denver #2"], ["visit", 2, "Denver #2"], ["visit", 2, "Denver #2"], ["visit", 2, "Denver #2"], ["visit", 2, "Denver #2"], ["visit", 2, "Denver #2"], ["visit", 2, "Denver #2"], ["visit", 2, "Denver #2"], ["visit", 1, "Boston"], ["visit", 1, "Boston"], ["visit", 1, "Boston"], ["visit", 1, "Boston"], ["visit", 1, "Boston"], ["visit", 1, "Boston"], ["visit", 1, "Boston"], ["visit", 1, "Boston"], ["visit", 1, "Boston"], ["visit", 1, "Boston"], ["visit", 2, "Boston"], ["visit", 2, "Boston"], ["visit", 2, "Boston"], ["visit", 2, "Boston"], ["visit", 2, "Boston"], ["visit", 2, "Boston"], ["visit", 2, "Boston"], ["visit", 2, "Boston"], ["visit", 2, "Boston"], ["visit", 2, "Boston"], ["visit", 2, "Boston"], ["visit", 2, "Boston"], ["visit", 2, "Boston"], ["visit", 2, "Boston"], ["visit", 2, "Boston"], ["visit", 2, "Boston"], ["visit", 2, "Boston"], ["visit", 2, "Boston"], ["visit", 2, "Boston"], ["visit", 2, "Boston"], ["visit", 2, "Boston"], ["visit", 2, "Boston"], ["visit", 2, "Boston"], ["visit", 2, "Boston"], ["visit", 2, "Boston"], ["visit", 2, "Boston"], ["visit", 2, "Boston"], ["visit", 2, "Boston"], ["visit", 2, "Boston"], ["visit", 2, "Boston"]], "Accuracies": ["False", "False", "False", "True", "True", "False", "False", "False", "False", "True", "True", "False", "False", "True", "False", "False", "False", "Syntax Error", "False", "False", "True", "True", "True", "True", "False", "True", "True", "False", "False", "True", "False", "True", "False", "False", "True", "True", "True", "True", "True", "True"], "Accumulated Accuracy": 0.475}